assert_typecheck/__init__.py
assert_typecheck/_version.py
assert_typecheck/assert_mypy.py
assert_typecheck/util.py
assert_typecheck-0.1.0.dist-info/LICENSE
assert_typecheck-0.1.0.dist-info/WHEEL
assert_typecheck-0.1.0.dist-info/METADATA
assert_typecheck-0.1.0.dist-info/RECORD
